django_customize_history/__init__.py
django_customize_history/admin.py
django_customize_history/templates/django_customize_history/object_history.html
django_customize_history1-1.0.1.dist-info/LICENSE
django_customize_history1-1.0.1.dist-info/METADATA
django_customize_history1-1.0.1.dist-info/WHEEL
django_customize_history1-1.0.1.dist-info/top_level.txt
django_customize_history1-1.0.1.dist-info/RECORD
