Metadata-Version: 2.1
Name: django-customize-history1
Version: 1.0.1
Summary: UNKNOWN
Home-page: https://github.com/mayur-softices/djnago-customize-history/
Author: Mayur Ariwala
Author-email: mayur@softices.com
License: MIT
Keywords: Django Customize History
Platform: UNKNOWN
Requires-Dist: django
